corgi_cli/__init__.py
corgi_cli/corgi.py
corgi_cli-1.0.0.dist-info/METADATA
corgi_cli-1.0.0.dist-info/WHEEL
corgi_cli-1.0.0.dist-info/entry_points.txt
corgi_cli-1.0.0.dist-info/top_level.txt
corgi_cli-1.0.0.dist-info/RECORD
