Metadata-Version: 2.1
Name: corgi-cli
Version: 1.0.0
Summary: A modern doggo.ninja cli.
Home-page: https://github.com/l3gacyb3ta/corgi
Author: Raleigh Wise
Author-email: vibhu4agarwal@gmail.com
License: UNLICENSE
Keywords: doggo.ninja doggo ninja cli bone
Platform: UNKNOWN
Classifier: Programming Language :: Python :: 3
Classifier: Operating System :: OS Independent
Requires-Dist: python-magic
Requires-Dist: requests
Requires-Dist: docopt
Requires-Dist: pyinstaller
